se_imports/__init__.py
se_imports/se_code.py
se_imports/se_run.py
se_imports/test_py.py
se_imports-0.1.1.dist-info/METADATA
se_imports-0.1.1.dist-info/WHEEL
se_imports-0.1.1.dist-info/top_level.txt
se_imports-0.1.1.dist-info/RECORD
